dfplayer/__init__.py
dfplayer/__main__.py
micropython_dfplayer-1.0.5.dist-info/LICENSE
micropython_dfplayer-1.0.5.dist-info/METADATA
micropython_dfplayer-1.0.5.dist-info/WHEEL
micropython_dfplayer-1.0.5.dist-info/top_level.txt
micropython_dfplayer-1.0.5.dist-info/RECORD
