Metadata-Version: 2.1
Name: micropython-dfplayer
Version: 1.0.5
Summary: Library to use the DFPlayer mini mp3 player module with micropython
Author-email: redoxcode <redoxcode@github.com>
License: MIT License
Project-URL: Homepage, https://github.com/redoxcode/micropython-dfplayer
Keywords: dfmini,dfplayer,mp3
Classifier: License :: OSI Approved :: MIT License
Classifier: Programming Language :: Python :: Implementation :: MicroPython
License-File: LICENSE
Provides-Extra: dev
